xmldsig/__init__.py
xmldsig/api.py
m3_xmldsig-1.0.2.dist-info/LICENSE
m3_xmldsig-1.0.2.dist-info/METADATA
m3_xmldsig-1.0.2.dist-info/WHEEL
m3_xmldsig-1.0.2.dist-info/top_level.txt
m3_xmldsig-1.0.2.dist-info/RECORD
