Metadata-Version: 2.1
Name: m3-xmldsig
Version: 1.0.2
Summary: Sign and verify RSA-SHA1 XML Digital Signatures
Home-page: https://bitbucket.org/barsgroup/xmldsig
Author: BARS Group
Author-email: kirov@bars-open.ru
License: MIT
Platform: UNKNOWN
Classifier: Intended Audience :: Developers
Classifier: Environment :: Web Environment
Classifier: Natural Language :: Russian
Classifier: Natural Language :: English
Classifier: Operating System :: OS Independent
Classifier: Programming Language :: Python
Classifier: License :: OSI Approved :: MIT License
Classifier: Development Status :: 5 - Production/Stable
License-File: LICENSE
Requires-Dist: lxml (>=3.0)
Requires-Dist: rsa (>=3.1.1)
Requires-Dist: six (>=1.10.0)
